<?xml version="1.0"?>
<fr-patent-document family-id="1800144903" date-produced="20240105" kind="A1" doc-number="3137468" country="FR" id="2206566" status="NEW" dtd-version="1.6.0" lang="fr">
  <fr-bibliographic-data>
    <fr-publication-data>
      <fr-publication-reference data-format="inpi">
        <document-id>
          <country>FR</country>
          <doc-number>3137468</doc-number>
          <kind>A1</kind>
          <date>20240105</date>
        </document-id>
        <fr-bopinum>2024-01</fr-bopinum>
        <fr-nature>Demande fran&#xE7;aise</fr-nature>
      </fr-publication-reference>
    </fr-publication-data>
    <fr-application-reference data-format="inpi" doc-id="800144903">
      <document-id>
        <country>FR</country>
        <doc-number>2206566</doc-number>
        <date>20220629</date>
      </document-id>
    </fr-application-reference>
    <fr-application-reference data-format="docdb">
      <document-id>
        <country>FR</country>
        <doc-number>2206566</doc-number>
        <date>20220629</date>
      </document-id>
    </fr-application-reference>
    <invention-title lang="fr">PROCEDE DE GESTION D&#x2019;UN COMPTEUR COMMUNICANT</invention-title>
    <parties>
      <applicants>
        <applicant designation="all" app-type="applicant" data-format="liste" sequence="1">
          <addressbook lang="fr">
            <orgname>SAGEMCOM ENERGY &amp; TELECOM</orgname>
            <address>
              <address-1>250 Route de l'Empereur</address-1>
              <city>RUEIL MALMAISON</city>
              <postcode>92500</postcode>
              <country>FR</country>
            </address>
          </addressbook>
        </applicant>
      </applicants>
      <inventors>
        <inventor data-format="liste" sequence="1">
          <addressbook lang="fr">
            <last-name>ABID</last-name>
            <first-name>Oussama</first-name>
            <address>
              <address-1/>
              <city>RUEIL MALMAISON</city>
              <postcode>92500</postcode>
              <country>FR</country>
            </address>
          </addressbook>
        </inventor>
        <inventor data-format="liste" sequence="2">
          <addressbook lang="fr">
            <last-name>SABRAOUI</last-name>
            <first-name>Abbas</first-name>
            <address>
              <address-1/>
              <city>RUEIL MALMAISON</city>
              <postcode>92500</postcode>
              <country>FR</country>
            </address>
          </addressbook>
        </inventor>
        <inventor data-format="liste" sequence="3">
          <addressbook lang="fr">
            <last-name>BASTURK</last-name>
            <first-name>Ahmet Samet</first-name>
            <address>
              <address-1/>
              <city>RUEIL MALMAISON</city>
              <postcode>92500</postcode>
              <country>FR</country>
            </address>
          </addressbook>
        </inventor>
      </inventors>
      <agents>
        <agent rep-type="agent" sequence="1">
          <addressbook lang="fr">
            <orgname>CABINET LE GUEN &amp; ASSOCIES</orgname>
            <address>
              <address-1>3 Impasse de la Vigie CS 71840</address-1>
              <city>SAINT-MALO Cedex</city>
              <postcode>35418</postcode>
              <country>FR</country>
            </address>
          </addressbook>
        </agent>
      </agents>
    </parties>
    <fr-owners>
      <fr-owner sequence="1">
        <addressbook lang="fr">
          <orgname>SAGEMCOM ENERGY &amp; TELECOM</orgname>
          <address>
            <address-1>250 Route de l'Empereur</address-1>
            <city>RUEIL MALMAISON</city>
            <postcode>92500</postcode>
            <country>FR</country>
          </address>
        </addressbook>
      </fr-owner>
    </fr-owners>
    <classifications-ipcr>
      <classification-ipcr sequence="1">
        <text>G06F   1/26        20220101AFI20220926BHFR        </text>
      </classification-ipcr>
      <classification-ipcr sequence="2">
        <text>G01F   1/00        20220101ALI20220926BHFR        </text>
      </classification-ipcr>
    </classifications-ipcr>
    <language-of-filing>fr</language-of-filing>
  </fr-bibliographic-data>
  <abstract lang="fr">
    <p>
    Un proc&#xE9;d&#xE9; (100) de gestion d&#x2019;un compteur communicant aliment&#xE9; par pile, pour mesurer une consommation d&#x2019;un fluide, le compteur comportant une unit&#xE9; de mesure pour acqu&#xE9;rir des mesures de consommation du fluide.Le compteur dispose de trois modes op&#xE9;ratoires :-     un mode de fonctionnement nominal dans lequel l&#x2019;unit&#xE9; de mesure effectue des mesures &#xE0; une fr&#xE9;quence nominale pr&#xE9;d&#xE9;termin&#xE9;e,-     un mode de fonctionnement d&#xE9;grad&#xE9; dans lequel l&#x2019;unit&#xE9; de mesure effectue des mesures &#xE0; une fr&#xE9;quence d&#xE9;grad&#xE9;e pr&#xE9;d&#xE9;termin&#xE9;e inf&#xE9;rieure &#xE0; la fr&#xE9;quence nominale, et -     un mode de fonctionnement minimal dans lequel l&#x2019;unit&#xE9; de mesure effectue des mesures &#xE0; la fr&#xE9;quence d&#xE9;grad&#xE9;e pr&#xE9;d&#xE9;termin&#xE9;e,et une unit&#xE9; de contr&#xF4;le du compteur effectue les &#xE9;tapes suivantes :-     effectuer une estimation de la capacit&#xE9; restante de la pile du compteur ;-     commander le passage du compteur du mode de fonctionnement nominal vers le mode de fonctionnement d&#xE9;grad&#xE9; lorsque ladite estimation est inf&#xE9;rieure ou &#xE9;gale &#xE0; un premier seuil (T1) ; et-     commander le passage du compteur du mode de fonctionnement d&#xE9;grad&#xE9; vers le mode de fonctionnement minimal lorsque ladite estimation est inf&#xE9;rieure ou &#xE9;gale &#xE0; un second seuil (T2).
    Figure &#xE0; publier avec l&#x2019;abr&#xE9;g&#xE9;&#xA0;: Fig. 3
  </p>
  </abstract>
  <fr-patent-life>
    <fr-date-availability>
      <fr-last-fee-payement percentile="2">
        <date>20230523</date>
      </fr-last-fee-payement>
      <fr-next-fee-payement percentile="3">
        <date>20240701</date>
      </fr-next-fee-payement>
      <fr-date-search-completed>
        <date>20240105</date>
        <fr-bopinum>2024-01</fr-bopinum>
      </fr-date-search-completed>
    </fr-date-availability>
  </fr-patent-life>
</fr-patent-document>
