<?xml version="1.0"?>
<fr-patent-document family-id="1800144844" date-produced="20240105" kind="A1" doc-number="3137493" country="FR" id="2206501" status="NEW" dtd-version="1.6.0" lang="fr">
  <fr-bibliographic-data>
    <fr-publication-data>
      <fr-publication-reference data-format="inpi">
        <document-id>
          <country>FR</country>
          <doc-number>3137493</doc-number>
          <kind>A1</kind>
          <date>20240105</date>
        </document-id>
        <fr-bopinum>2024-01</fr-bopinum>
        <fr-nature>Demande fran&#xE7;aise</fr-nature>
      </fr-publication-reference>
    </fr-publication-data>
    <fr-application-reference data-format="inpi" doc-id="800144844">
      <document-id>
        <country>FR</country>
        <doc-number>2206501</doc-number>
        <date>20220629</date>
      </document-id>
    </fr-application-reference>
    <fr-application-reference data-format="docdb">
      <document-id>
        <country>FR</country>
        <doc-number>2206501</doc-number>
        <date>20220629</date>
      </document-id>
    </fr-application-reference>
    <invention-title lang="fr">PROCEDE DE FABRICATION D&#x2019;UNE STRUCTURE COMPORTANT UNE COUCHE BARRIERE A LA DIFFUSION D&#x2019;ESPECES ATOMIQUES</invention-title>
    <parties>
      <applicants>
        <applicant designation="all" app-type="applicant" data-format="liste" sequence="1">
          <addressbook lang="fr">
            <orgname>SOITEC</orgname>
            <iid>384711909</iid>
            <address>
              <address-1>PARC TECHNOLOGIQUE DES FONTAINES CHEMIN DES FRANQUES</address-1>
              <city>BERNIN</city>
              <postcode>38190</postcode>
              <country>FR</country>
            </address>
          </addressbook>
        </applicant>
        <applicant designation="all" app-type="applicant" data-format="liste" sequence="2">
          <addressbook lang="fr">
            <orgname>COMMISSARIAT A L'ENERGIE ATOMIQUE ET AUX ENERGIES ALTERNATIVES</orgname>
            <iid>775685019</iid>
            <address>
              <address-1>25 rue Leblanc BAT LE PONANT</address-1>
              <city>PARIS</city>
              <postcode>75015</postcode>
              <country>FR</country>
            </address>
          </addressbook>
        </applicant>
      </applicants>
      <inventors>
        <inventor data-format="liste" sequence="1">
          <addressbook lang="fr">
            <last-name>MOUREY</last-name>
            <first-name>Odile</first-name>
            <address>
              <address-1/>
              <city>BERNIN</city>
              <postcode>38190</postcode>
              <country>FR</country>
            </address>
          </addressbook>
        </inventor>
        <inventor data-format="liste" sequence="2">
          <addressbook lang="fr">
            <last-name>CAPELLO</last-name>
            <first-name>Luciana</first-name>
            <address>
              <address-1/>
              <city>BERNIN</city>
              <postcode>38190</postcode>
              <country>FR</country>
            </address>
          </addressbook>
        </inventor>
        <inventor data-format="liste" sequence="3">
          <addressbook lang="fr">
            <last-name>HUYET</last-name>
            <first-name>Isabelle</first-name>
            <address>
              <address-1/>
              <city>BERNIN</city>
              <postcode>38190</postcode>
              <country>FR</country>
            </address>
          </addressbook>
        </inventor>
        <inventor data-format="liste" sequence="4">
          <addressbook lang="fr">
            <last-name>KERDILES</last-name>
            <first-name>S&#xE9;bastien</first-name>
            <address>
              <address-1/>
              <city>GRENOBLE CEDEX 9</city>
              <postcode>38054</postcode>
              <country>FR</country>
            </address>
          </addressbook>
        </inventor>
        <inventor data-format="liste" sequence="5">
          <addressbook lang="fr">
            <last-name>LEFORESTIER</last-name>
            <first-name>Soazig</first-name>
            <address>
              <address-1/>
              <city>GRENOBLE CEDEX 9</city>
              <postcode>38054</postcode>
              <country>FR</country>
            </address>
          </addressbook>
        </inventor>
      </inventors>
      <agents>
        <agent rep-type="agent" sequence="1">
          <addressbook lang="fr">
            <orgname>IP TRUST</orgname>
            <address>
              <address-1>2 rue de Clichy</address-1>
              <city>PARIS</city>
              <postcode>75009</postcode>
              <country>FR</country>
            </address>
          </addressbook>
        </agent>
      </agents>
    </parties>
    <fr-owners>
      <fr-owner sequence="1">
        <addressbook lang="fr">
          <orgname>SOITEC</orgname>
          <iid>384711909</iid>
          <address>
            <address-1>PARC TECHNOLOGIQUE DES FONTAINES CHEMIN DES FRANQUES</address-1>
            <city>BERNIN</city>
            <postcode>38190</postcode>
            <country>FR</country>
          </address>
        </addressbook>
      </fr-owner>
      <fr-owner sequence="2">
        <addressbook lang="fr">
          <orgname>COMMISSARIAT A L'ENERGIE ATOMIQUE ET AUX ENERGIES ALTERNATIVES</orgname>
          <iid>775685019</iid>
          <address>
            <address-1>25 rue Leblanc BAT LE PONANT</address-1>
            <city>PARIS</city>
            <postcode>75015</postcode>
            <country>FR</country>
          </address>
        </addressbook>
      </fr-owner>
    </fr-owners>
    <classifications-ipcr>
      <classification-ipcr sequence="1">
        <text>H01L  21/762       20220101AFI20221014BHFR        </text>
      </classification-ipcr>
      <classification-ipcr sequence="2">
        <text>H01L  21/02        20220101ALI20221014BHFR        </text>
      </classification-ipcr>
      <classification-ipcr sequence="3">
        <text>H01L  29/02        20220101ALI20221014BHFR        </text>
      </classification-ipcr>
      <classification-ipcr sequence="4">
        <text>H01L  27/02        20220101ALI20221014BHFR        </text>
      </classification-ipcr>
      <classification-ipcr sequence="5">
        <text>H01L  27/20        20220101ALI20221014BHFR        </text>
      </classification-ipcr>
    </classifications-ipcr>
    <language-of-filing>fr</language-of-filing>
  </fr-bibliographic-data>
  <abstract lang="fr">
    <p>
    L&#x2019;invention porte sur une structure (1) comprenant un support (2) form&#xE9; d&#x2019;une couche de pi&#xE9;geage de charges &#xE9;lectriques (2b) dispos&#xE9;e superficiellement sur un substrat de base (2a) et comprenant une couche mince (4) report&#xE9;e sur le support (2). La structure (1) comprend une couche di&#xE9;lectrique intercalaire (3) dispos&#xE9;e entre et en contact avec le support (2) et la couche mince (4). La couche di&#xE9;lectrique intercalaire (3) comprend une premi&#xE8;re couche di&#xE9;lectrique (31) dispos&#xE9;e sur et en contact avec la couche de pi&#xE9;geage (2b), une couche barri&#xE8;re (5) en nitrure de silicium dispos&#xE9;e sur et en contact avec la premi&#xE8;re couche di&#xE9;lectrique (31), une deuxi&#xE8;me couche di&#xE9;lectrique (32) dispos&#xE9;e sur et en contact avec la couche barri&#xE8;re (5).
    Figure &#xE0; publier avec l&#x2019;abr&#xE9;g&#xE9;&#xA0;: Fig. 1
  </p>
  </abstract>
  <fr-patent-life>
    <references-cited>
      <citation>
        <patcit>
          <text>US 2018/114720 A1 (WANG GANG [US] ET AL)
26 avril 2018 (2018-04-26)</text>
          <document-id>
            <country>US</country>
            <doc-number>US-2018114720-A1</doc-number>
            <date>20180426</date>
          </document-id>
        </patcit>
      </citation>
      <citation>
        <patcit>
          <text>WO 2022/023630 A1 (SOITEC SILICON ON
INSULATOR [FR])
3 f&#xE9;vrier 2022 (2022-02-03)</text>
          <document-id>
            <country>WO</country>
            <doc-number>WO-2022023630-A1</doc-number>
            <date>20220203</date>
          </document-id>
        </patcit>
      </citation>
      <citation>
        <patcit>
          <text>US 2018/158721 A1 (LIBBERT JEFFERY L [US]
ET AL) 7 juin 2018 (2018-06-07)</text>
          <document-id>
            <country>US</country>
            <doc-number>US-2018158721-A1</doc-number>
            <date>20180607</date>
          </document-id>
        </patcit>
      </citation>
    </references-cited>
    <fr-date-availability>
      <fr-last-fee-payement percentile="2">
        <date>20230523</date>
      </fr-last-fee-payement>
      <fr-next-fee-payement percentile="3">
        <date>20240701</date>
      </fr-next-fee-payement>
      <fr-date-search-completed>
        <date>20240105</date>
        <fr-bopinum>2024-01</fr-bopinum>
      </fr-date-search-completed>
    </fr-date-availability>
  </fr-patent-life>
</fr-patent-document>
